advent_of_code_wim-2025.12.dist-info/licenses/LICENSE
aoc_wim/__init__.py
aoc_wim/autoparse.py
aoc_wim/cli.py
aoc_wim/ocr.py
aoc_wim/search.py
aoc_wim/stuff.py
aoc_wim/util.py
aoc_wim/zgrid.py
aoc_wim/aoc2015/__init__.py
aoc_wim/aoc2015/q01.py
aoc_wim/aoc2015/q02.py
aoc_wim/aoc2015/q03.py
aoc_wim/aoc2015/q04.py
aoc_wim/aoc2015/q05.py
aoc_wim/aoc2015/q06.py
aoc_wim/aoc2015/q07.py
aoc_wim/aoc2015/q08.py
aoc_wim/aoc2015/q09.py
aoc_wim/aoc2015/q10.py
aoc_wim/aoc2015/q11.py
aoc_wim/aoc2015/q12.py
aoc_wim/aoc2015/q13.py
aoc_wim/aoc2015/q14.py
aoc_wim/aoc2015/q15.py
aoc_wim/aoc2015/q16.py
aoc_wim/aoc2015/q17.py
aoc_wim/aoc2015/q18.py
aoc_wim/aoc2015/q19.py
aoc_wim/aoc2015/q20.py
aoc_wim/aoc2015/q21.py
aoc_wim/aoc2015/q22.py
aoc_wim/aoc2015/q23.py
aoc_wim/aoc2015/q24.py
aoc_wim/aoc2015/q25.py
aoc_wim/aoc2016/__init__.py
aoc_wim/aoc2016/q01.py
aoc_wim/aoc2016/q02.py
aoc_wim/aoc2016/q03.py
aoc_wim/aoc2016/q04.py
aoc_wim/aoc2016/q05.py
aoc_wim/aoc2016/q05_single_core.py
aoc_wim/aoc2016/q06.py
aoc_wim/aoc2016/q07.py
aoc_wim/aoc2016/q08.py
aoc_wim/aoc2016/q09.py
aoc_wim/aoc2016/q10.py
aoc_wim/aoc2016/q11.py
aoc_wim/aoc2016/q12.py
aoc_wim/aoc2016/q13.py
aoc_wim/aoc2016/q14.py
aoc_wim/aoc2016/q14_single_core.py
aoc_wim/aoc2016/q15.py
aoc_wim/aoc2016/q16.py
aoc_wim/aoc2016/q17.py
aoc_wim/aoc2016/q18.py
aoc_wim/aoc2016/q19.py
aoc_wim/aoc2016/q20.py
aoc_wim/aoc2016/q21.py
aoc_wim/aoc2016/q22.py
aoc_wim/aoc2016/q23.py
aoc_wim/aoc2016/q24.py
aoc_wim/aoc2016/q25.py
aoc_wim/aoc2017/__init__.py
aoc_wim/aoc2017/q01.py
aoc_wim/aoc2017/q02.py
aoc_wim/aoc2017/q03.py
aoc_wim/aoc2017/q04.py
aoc_wim/aoc2017/q05.py
aoc_wim/aoc2017/q06.py
aoc_wim/aoc2017/q07.py
aoc_wim/aoc2017/q08.py
aoc_wim/aoc2017/q08_crazy.py
aoc_wim/aoc2017/q09.py
aoc_wim/aoc2017/q10.py
aoc_wim/aoc2017/q11.py
aoc_wim/aoc2017/q12.py
aoc_wim/aoc2017/q12_quadratic.py
aoc_wim/aoc2017/q13.py
aoc_wim/aoc2017/q14.py
aoc_wim/aoc2017/q15.py
aoc_wim/aoc2017/q15_numba.py
aoc_wim/aoc2017/q15_slow.py
aoc_wim/aoc2017/q16.py
aoc_wim/aoc2017/q17.py
aoc_wim/aoc2017/q18.py
aoc_wim/aoc2017/q19.py
advent_of_code_wim-2025.12.dist-info/METADATA
advent_of_code_wim-2025.12.dist-info/WHEEL
advent_of_code_wim-2025.12.dist-info/entry_points.txt
advent_of_code_wim-2025.12.dist-info/top_level.txt
advent_of_code_wim-2025.12.dist-info/RECORD
